Metadata-Version: 2.1
Name: odoo12-addon-l10n_be_vat_reports
Version: 12.0.2.0.3
Summary: Belgium VAT Reports
Home-page: https://github.com/OCA/l10n-belgium
Author: ACSONE SA/NV, Coop IT Easy SCRLfs, Odoo SA, Odoo Community Association (OCA)
Author-email: support@odoo-community.org
License: AGPL-3
Classifier: Programming Language :: Python
Classifier: Framework :: Odoo
Classifier: Framework :: Odoo :: 12.0
Classifier: License :: OSI Approved :: GNU Affero General Public License v3
Requires-Python: >=3.5
Requires-Dist: odoo12-addon-report-xml
Requires-Dist: odoo<12.1dev,>=12.0a
